pypresence/__init__.py
pypresence/baseclient.py
pypresence/client.py
pypresence/exceptions.py
pypresence/payloads.py
pypresence/presence.py
pypresence/py.typed
pypresence/types.py
pypresence/utils.py
pypresence-4.6.0.dist-info/licenses/LICENSE
pypresence-4.6.0.dist-info/METADATA
pypresence-4.6.0.dist-info/WHEEL
pypresence-4.6.0.dist-info/top_level.txt
pypresence-4.6.0.dist-info/zip-safe
pypresence-4.6.0.dist-info/RECORD
